[{"id":"aset-foto","name":"aset-foto","public":false,"created_at":"2026-06-05T12:44:42.092298+00:00"}, {"id":"berkas-permohonan","name":"berkas-permohonan","public":false,"created_at":"2026-06-05T12:44:42.092298+00:00"}, {"id":"form-submissions","name":"form-submissions","public":false,"created_at":"2026-06-05T12:53:10.395762+00:00"}, {"id":"pejabat-foto","name":"pejabat-foto","public":true,"created_at":"2026-06-05T12:44:42.092298+00:00"}, {"id":"share-files","name":"share-files","public":false,"created_at":"2026-06-05T12:50:26.714982+00:00"}]
